LICENSE
MANIFEST.in
README.md
demo.ipynb
setup.py
astro_forecaster.egg-info/PKG-INFO
astro_forecaster.egg-info/SOURCES.txt
astro_forecaster.egg-info/dependency_links.txt
astro_forecaster.egg-info/requires.txt
astro_forecaster.egg-info/top_level.txt
forecaster/__init__.py
forecaster/fitting_parameters.h5
forecaster/forecaster.py