Metadata-Version: 2.1
Name: astro-forecaster
Version: 2.0.2
Summary: Probabilistically forecast astronomical masses and radii
Home-page: https://github.com/ben-cassese/astro-forecaster
Author: Ben Cassese
Author-email: b.c.cassese@columbia.edu
License: MIT
License-File: LICENSE
